scenario_thinker-0.1.1.2.data/scripts/extra_modules.py
scenario_thinker-0.1.1.2.data/scripts/st_prepare
scenario_thinker-0.1.1.2.dist-info/licenses/LICENSE
st_preparation/copy_files.py
st_preparation/files_to_copy_into_user/.env
st_preparation/files_to_copy_into_user/app.py
st_preparation/files_to_copy_into_user/index.css
st_preparation/files_to_copy_into_user/index.html
st_preparation/files_to_copy_into_user/script.js
st_preparation/files_to_copy_into_user/settings.css
st_preparation/files_to_copy_into_user/settings.html
st_preparation/files_to_copy_into_user/settings_script.js
st_preparation/services/services/bdd_step_file_creator.py
st_preparation/services/services/chatgpt_35_turbo_service.py
st_preparation/services/services/chatgpt_4_service.py
st_preparation/services/services/chatgpt_4o_service.py
st_preparation/services/services/chatgpt_service.py
st_preparation/services/services/claude_haiku_service.py
st_preparation/services/services/claude_opus_service.py
st_preparation/services/services/claude_service.py
st_preparation/services/services/constants.py
st_preparation/services/services/copy_claude_service.py
st_preparation/services/services/database.py
st_preparation/services/services/dummy_chatgpt_service.py
st_preparation/services/services/google_gemma_service.py
st_preparation/services/services/grok_service.py
st_preparation/services/services/llama_7b_service.py
st_preparation/services/services/llama_service.py
st_preparation/services/services/llama_turbo_service.py
st_preparation/services/services/mistral_nemo_service.py
st_preparation/services/services/ollama_service.py
st_preparation/services/services/parse_scenario.py
st_preparation/services/services/scenario_creator.py
st_preparation/services/services/testing_service.py
scenario_thinker-0.1.1.2.dist-info/METADATA
scenario_thinker-0.1.1.2.dist-info/WHEEL
scenario_thinker-0.1.1.2.dist-info/top_level.txt
scenario_thinker-0.1.1.2.dist-info/RECORD
