Metadata-Version: 2.4
Name: scenario_thinker
Version: 0.1.1.2
Summary: BDD and AI library
Home-page: https://github.com/me3eh/scenario_thinker
Author: Me3eh
Author-email: matt30002000@gmail.com
Classifier: Programming Language :: Python :: 3
Classifier: License :: OSI Approved :: MIT License
Classifier: Operating System :: OS Independent
License-File: LICENSE
Requires-Dist: behave>=1.2.5
Requires-Dist: selenium>=4.26.1
Requires-Dist: flask>=3.0.3
Requires-Dist: Flask-Cors>=5.0.0
Requires-Dist: ipdb>=0.13.13
Requires-Dist: requests>=2.31.0
Requires-Dist: dotenv>=0.0.5
Dynamic: author
Dynamic: author-email
Dynamic: classifier
Dynamic: description
Dynamic: description-content-type
Dynamic: home-page
Dynamic: license-file
Dynamic: requires-dist
Dynamic: summary
